django_audit_log_middleware/__init__.py
django_audit_log_middleware/test/__init__.py
django_audit_log_middleware/test/test_middleware.py
django_audit_log_middleware-0.0.5.dist-info/LICENSE
django_audit_log_middleware-0.0.5.dist-info/METADATA
django_audit_log_middleware-0.0.5.dist-info/WHEEL
django_audit_log_middleware-0.0.5.dist-info/top_level.txt
django_audit_log_middleware-0.0.5.dist-info/RECORD
