Metadata-Version: 2.1
Name: django_audit_log_middleware
Version: 0.0.5
Summary: Simple audit logging for Django requests
Home-page: https://github.com/uktrade/django-audit-log-middleware
Author: Ross Miller
Author-email: ross.miller@digita.trade.gov.uk
Classifier: Programming Language :: Python :: 3
Classifier: License :: OSI Approved :: MIT License
Classifier: Operating System :: OS Independent
Requires-Python: >=3.8
License-File: LICENSE
Requires-Dist: django>=2.2.0
Requires-Dist: django-ipware>=3.0.2
